nomad_camels/.coverage
nomad_camels/CAMELS_start.py
nomad_camels/MainApp_v2.py
nomad_camels/__init__.py
nomad_camels/__main__.py
nomad_camels/api/api.py
nomad_camels/api/api_schema.yaml
nomad_camels/api/api_schema_validation.py
nomad_camels/api/using_api.py
nomad_camels/bluesky_handling/EpicsFieldSignal.py
nomad_camels/bluesky_handling/TriggerEpicsSignalRO.py
nomad_camels/bluesky_handling/__init__.py
nomad_camels/bluesky_handling/builder_helper_functions.py
nomad_camels/bluesky_handling/custom_function_signal.py
nomad_camels/bluesky_handling/evaluation_helper.py
nomad_camels/bluesky_handling/flyer_interface.py
nomad_camels/bluesky_handling/helper_functions.py
nomad_camels/bluesky_handling/loop_step_functions_api_call.py
nomad_camels/bluesky_handling/make_catalog.py
nomad_camels/bluesky_handling/protocol_builder.py
nomad_camels/bluesky_handling/run_engine_overwrite.py
nomad_camels/bluesky_handling/variable_reading.py
nomad_camels/bluesky_handling/visa_signal.py
nomad_camels/bluesky_handling/watchdogs.py
nomad_camels/commands/__init__.py
nomad_camels/commands/change_sequence.py
nomad_camels/extensions/__init__.py
nomad_camels/extensions/extension_contexts.py
nomad_camels/extensions/extension_interface.py
nomad_camels/extensions/extension_management.py
nomad_camels/frontpanels/__init__.py
nomad_camels/frontpanels/flyer_window.py
nomad_camels/frontpanels/helper_panels/__init__.py
nomad_camels/frontpanels/helper_panels/button_move_scroll_area.py
nomad_camels/frontpanels/helper_panels/enterTextDialog.py
nomad_camels/frontpanels/helper_panels/pass_ask.py
nomad_camels/frontpanels/instrument_aliases.py
nomad_camels/frontpanels/instrument_config.py
nomad_camels/frontpanels/instrument_installer.py
nomad_camels/frontpanels/manage_instruments.py
nomad_camels/frontpanels/plot_definer.py
nomad_camels/frontpanels/protocol_config.py
nomad_camels/frontpanels/settings_window.py
nomad_camels/graphics/CAMELS.ico
nomad_camels/graphics/CAMELS_Icon.png
nomad_camels-1.10.3.dist-info/METADATA
nomad_camels-1.10.3.dist-info/WHEEL
nomad_camels-1.10.3.dist-info/entry_points.txt
nomad_camels-1.10.3.dist-info/licenses/LICENSE
nomad_camels-1.10.3.dist-info/RECORD
