Metadata-Version: 2.4
Name: nomad_camels
Version: 1.10.3
Summary: CAMELS is a configurable measurement software, targeted towards the requirements of experimental solid-state physics.
License-File: LICENSE
Author: FAIRmat - HU Berlin
Author-email: nomad-camels@fau.de
Requires-Python: >=3.9,<3.13
Classifier: Programming Language :: Python :: 3
Classifier: License :: OSI Approved :: GNU Lesser General Public License v2 (LGPLv2)
Provides-Extra: api
Provides-Extra: dash
Provides-Extra: dev
Provides-Extra: material
Provides-Extra: visa
Requires-Dist: bluesky (>=1.9.0)
Requires-Dist: dash (>=2.7.0) ; extra == "dash"
Requires-Dist: databroker (>=1.2.5)
Requires-Dist: fastapi (>=0.110.1) ; extra == "api"
Requires-Dist: httpx (>=0.21.0) ; (python_version == "3.9") and (extra == "api")
Requires-Dist: httpx (>=0.28.1) ; (python_version >= "3.10") and (extra == "api")
Requires-Dist: lmfit (>=1.3.0)
Requires-Dist: matplotlib (>=3.6.2)
Requires-Dist: numpy (>=1.22.0,<2.1.0) ; python_version == "3.9"
Requires-Dist: numpy (>=1.23.0) ; python_version >= "3.10" and python_version < "3.12"
Requires-Dist: numpy (>=1.26.0) ; python_version >= "3.12"
Requires-Dist: ophyd (>=1.6.4)
Requires-Dist: psutil (>=6.0.0) ; extra == "visa"
Requires-Dist: pyqtgraph (>=0.13.3)
Requires-Dist: pyserial (>=3.0) ; extra == "visa"
Requires-Dist: pyside6 (>=6.6.0,<6.9)
Requires-Dist: pytest (>=7.0.0) ; (python_version == "3.9") and (extra == "dev")
Requires-Dist: pytest (>=7.3.2) ; (python_version >= "3.10") and (extra == "dev")
Requires-Dist: pytest-cov (>=6.0.0) ; extra == "dev"
Requires-Dist: pytest-mock (>=0.4.0) ; extra == "dev"
Requires-Dist: pytest-order (>=0.7.1) ; extra == "dev"
Requires-Dist: pytest-qt (>=4.2.0) ; extra == "dev"
Requires-Dist: pytest-timeout (>=1.3.1) ; extra == "dev"
Requires-Dist: pytest-xvfb (>=3.0.0) ; (sys_platform == "linux") and (extra == "dev")
Requires-Dist: pyusb (>=1.2.0) ; extra == "visa"
Requires-Dist: pyvisa (>=1.12.0) ; extra == "visa"
Requires-Dist: pyvisa-py (>=0.5.3) ; extra == "visa"
Requires-Dist: pyyaml (>=5.3.1) ; python_version == "3.9"
Requires-Dist: pyyaml (>=6.0) ; python_version >= "3.10" and python_version < "3.12"
Requires-Dist: pyyaml (>=6.0.1) ; python_version >= "3.12"
Requires-Dist: pyzmq (>=22.1.0) ; python_version == "3.9"
Requires-Dist: pyzmq (>=26.2.0) ; python_version >= "3.10" and python_version < "3.12"
Requires-Dist: pyzmq (>=26.2.0) ; python_version >= "3.12"
Requires-Dist: qt-material (>=2.12) ; extra == "material"
Requires-Dist: requests (>=2.26.0)
Requires-Dist: setuptools (>=36.0.1) ; python_version == "3.9"
Requires-Dist: setuptools (>=54.2.0) ; python_version >= "3.10" and python_version < "3.12"
Requires-Dist: setuptools (>=66.1.0) ; python_version >= "3.12"
Requires-Dist: suitcase-nomad-camels-hdf5 (>=1.3.1)
Requires-Dist: uvicorn (>=0.19.0,<0.22.0) ; (python_version >= "3.9" and python_version < "3.12") and (extra == "api")
Requires-Dist: uvicorn (>=0.22.0) ; (python_version >= "3.12") and (extra == "api")
Requires-Dist: zeroconf (>=0.70.0) ; extra == "visa"
Project-URL: Documentation, https://fau-lap.github.io/NOMAD-CAMELS/
Project-URL: GitHub Page, https://github.com/FAU-LAP/NOMAD-CAMELS
